pubkeeper/protocol/__init__.py
pubkeeper/protocol/brew_state.py
pubkeeper/protocol/client_protocol.py
pubkeeper/protocol/packet.py
pubkeeper/protocol/protocol.py
pubkeeper/protocol/server_protocol.py
pubkeeper.protocol-0.2.4.dist-info/DESCRIPTION.rst
pubkeeper.protocol-0.2.4.dist-info/METADATA
pubkeeper.protocol-0.2.4.dist-info/RECORD
pubkeeper.protocol-0.2.4.dist-info/WHEEL
pubkeeper.protocol-0.2.4.dist-info/metadata.json
pubkeeper.protocol-0.2.4.dist-info/top_level.txt
